awsmfav2/__init__.py
awsmfav2/cli.py
tests/__init__.py
tests/test_cli.py
tests/test_data/config
tests/test_data/credentials_expired
tests/test_data/credentials_unexpired
aws_mfa_v2-0.3.5.dist-info/LICENSE
aws_mfa_v2-0.3.5.dist-info/METADATA
aws_mfa_v2-0.3.5.dist-info/WHEEL
aws_mfa_v2-0.3.5.dist-info/entry_points.txt
aws_mfa_v2-0.3.5.dist-info/RECORD
