Metadata-Version: 2.1
Name: aws-mfa-v2
Version: 0.3.5
Summary: Manage AWS MFA Security Credentials
Home-page: https://github.com/rkeiii/aws-mfa-v2
License: GPL-3.0-or-later
Author: Ron Ellis
Author-email: rkeiii@protonmail.com
Requires-Python: >=3.8,<4.0
Classifier: Development Status :: 5 - Production/Stable
Classifier: Environment :: Console
Classifier: License :: OSI Approved :: GNU General Public License v3 or later (GPLv3+)
Classifier: Operating System :: POSIX
Classifier: Programming Language :: Python :: 3
Classifier: Programming Language :: Python :: 3.8
Classifier: Programming Language :: Python :: 3.9
Classifier: Programming Language :: Python :: 3.10
Classifier: Programming Language :: Python :: 3.11
Provides-Extra: yubikey
Requires-Dist: boto3 (>=1.28.57,<2.0.0)
Requires-Dist: python-dateutil (>=2.8.2,<3.0.0)
Project-URL: Repository, https://github.com/rkeiii/aws-mfa-v2
